[
	{"lat":35.645240,  	"lng":139.719460, 	"name":"M2-01.恵比寿保健相談所（恵比寿社会教育館）","addr1":"",	"addr2":"",		"img":"system/data/port/M2-01.jpg",	"icon":"system/data/images/port.png"},
	{"lat":35.643606,  	"lng":139.713099,	"name":"M2-02.アメリカ橋公園",	"addr1":"","addr2":"",		"img":"system/data/port/M2-02.jpg",	"icon":"system/data/images/port.png"},
	{"lat":35.646581,  	"lng":139.710613,	"name":"M2-03.サイカパーク恵比寿",	"addr1":"","addr2":"",		"img":"system/data/port/M2-03.jpg",	"icon":"system/data/images/port.png"},	
	{"lat":35.653382,  	"lng":139.721059,	"name":"M2-04.広尾東公園","addr1":"",	"addr2":"",				"img":"system/data/port/M2-04.jpg",	"icon":"system/data/images/port.png"},
	{"lat":35.655190,  	"lng":139.718559, 	"name":"M2-05.日本赤十字医療センター","addr1":"",	"addr2":"",		"img":"system/data/port/M2-05.jpg",	"icon":"system/data/images/port.png"},
	{"lat":35.647237,  	"lng":139.71512, 	"name":"M2-06.あいおいニッセイ同和損保恵比寿ビル","addr1":"",	"addr2":"",		"img":"system/data/port/M2-06.jpg",	"icon":"system/data/images/port.png"},
	{"lat":35.657726,  	"lng":139.697802, 	"name":"M3-01.渋谷マークシティ","addr1":"",	"addr2":"",		"img":"system/data/port/M3-01.jpg",	"icon":"system/data/images/port.png"},
	{"lat":35.655510,  	"lng":139.699656,	"name":"M3-02.文化総合センター大和田","addr1":"",	"addr2":"",	"img":"system/data/port/M3-02.jpg",	"icon":"system/data/images/port.png"},
	{"lat":35.649823,  	"lng":139.700139, 	"name":"M3-03.代官山T-SITE","addr1":"",	"addr2":"",		"img":"system/data/port/M3-03.jpg",	"icon":"system/data/images/port.png"},	
	{"lat":35.648382,  	"lng":139.702005, 	"name":"M3-04.TENOHA代官山","addr1":"",	"addr2":"",		"img":"system/data/port/M3-04.jpg",	"icon":"system/data/images/port.png"},	
	{"lat":35.657589,  	"lng":139.705390, 	"name":"M3-05.渋谷3丁目","addr1":"",	"addr2":"",		"img":"system/data/port/M3-05.jpg",	"icon":"system/data/images/port.png"},	
	{"lat":35.657507,  	"lng":139.704393, 	"name":"M3-06.渋谷第一生命ビル","addr1":"",	"addr2":"",		"img":"system/data/port/M3-06.jpg",	"icon":"system/data/images/port.png"},	
	{"lat":35.655089,  	"lng":139.693851, 	"name":"M3-07.渋谷ファーストプレイス","addr1":"",	"addr2":"",		"img":"system/data/port/M3-07.jpg",	"icon":"system/data/images/port.png"},	
	{"lat":35.661475,  	"lng":139.699296, 	"name":"M3-09.ティップ.クロス TOKYO 渋谷","addr1":"",	"addr2":"",		"img":"system/data/port/M3-09.jpg",	"icon":"system/data/images/port.png"},
	{"lat":35.68714,  	"lng":139.702775,	"name":"M4-01.新宿タカシマヤ","addr1":"",	"addr2":"",	"img":"system/data/port/M4-01.jpg",	"icon":"system/data/images/port.png"},
	{"lat":35.684451,  	"lng":139.702884,	"name":"M4-03.NTTドコモ代々木ビル","addr1":"",	"addr2":"",	"img":"system/data/port/M4-03.jpg",	"icon":"system/data/images/port.png"},			
	{"lat":35.668345,  	"lng":139.705014,	"name":"M4-04.オリンピアアネックス","addr1":"",	"addr2":"",	"img":"system/data/port/M4-04.jpg",	"icon":"system/data/images/port.png"},			
	{"lat":35.662553,  	"lng":139.706763,	"name":"M4-05.TBSハウジング渋谷","addr1":"",	"addr2":"",	"img":"system/data/port/M4-05.jpg",	"icon":"system/data/images/port.png"},
	{"lat":35.67007,  	"lng":139.714168,	"name":"M4-06.RATIO＆Ｃ","addr1":"",	"addr2":"",	"img":"system/data/port/M4-06.jpg",	"icon":"system/data/images/counter.png"},
	{"lat":35.680154,  	"lng":139.685937,	"name":"M5-01.初台駅南口","addr1":"",	"addr2":"",				"img":"system/data/port/M5-01.jpg",	"icon":"system/data/images/port.png"},	
	{"lat":35.684423,  	"lng":139.692262,	"name":"M5-02.あいおいニッセイ同和損保新宿ビル","addr1":"","addr2":""	,	"img":"system/data/port/M5-02.jpg",	"icon":"system/data/images/port.png"},
	{"lat":35.671282,  	"lng":139.675307,	"name":"M5-03.代々木大山公園","addr1":"","addr2":""	,	"img":"system/data/port/M5-03.jpg",	"icon":"system/data/images/port.png"},
	{"lat":35.669970,  	"lng":139.686230,	"name":"M5-04.セブン-イレブン 元代々木町店","addr1":"","addr2":""	,	"img":"system/data/port/M5-04.jpg",	"icon":"system/data/images/port.png"},
	{"lat":35.665321,  	"lng":139.678627,	"name":"M5-05.セブン-イレブン 渋谷上原3丁目店","addr1":"","addr2":""	,	"img":"system/data/port/M5-05.jpg",	"icon":"system/data/images/port.png"},
	{"lat":35.677587,  	"lng":139.689599,	"name":"M5-07.カスタリア参宮橋","addr1":"","addr2":""	,	"img":"system/data/port/M5-07.jpg",	"icon":"system/data/images/port.png"},
	{"lat":35.677175,  	"lng":139.676769, 	"name":"M6-01.幡ヶ谷駅高架下第一","addr1":"",	"addr2":"",		"img":"system/data/port/M6-01.jpg",	"icon":"system/data/images/port.png"},
	{"lat":35.673444,  	"lng":139.666553, 	"name":"M6-02.サイカパーク笹塚","addr1":"",	"addr2":"",		"img":"system/data/port/M6-02.jpg",	"icon":"system/data/images/port.png"},
	{"lat":35.675198,   "lng":139.663587, 	"name":"M6-03.十三号通り公園","addr1":"",	"addr2":"",		"img":"system/data/port/M6-03.jpg",	"icon":"system/data/images/port.png"},
	{"lat":35.687126, 	"lng":139.680702, 	"name":"M6-04.本町東べんてん橋公園","addr1":"","addr2":""	,	"img":"system/data/port/M6-04.jpg",	"icon":"system/data/images/port.png"},
	{"lat":35.678881, 	"lng":139.674349, 	"name":"M6-05.七号通り公園","addr1":"",	"addr2":"",	"img":"system/data/port/M6-05.jpg",	"icon":"system/data/images/port.png"},
	{"lat":35.679155,  	"lng":139.669069,	"name":"M6-06.セブン-イレブン 笹塚店","addr1":"","addr2":""	,	"img":"system/data/port/M6-06.jpg",	"icon":"system/data/images/port.png"}
	]